{
	"boxOfficeResult": {
		"boxofficeType": "일별 박스오피스",
		"showRange": "20180730~20180730",
		"dailyBoxOfficeList": [
			{
				"rnum": "1",
				"rank": "1",
				"rankInten": "1",
				"rankOldAndNew": "OLD",
				"movieCd": "20185242",
				"movieNm": "신비아파트: 금빛 도깨비와 비밀의 동굴",
				"openDt": "2018-07-25",
				"salesAmt": "458460600",
				"salesShare": "44.5",
				"salesInten": "-288665300",
				"salesChange": "-38.6",
				"salesAcc": "2875030800",
				"audiCnt": "65555",
				"audiInten": "-29407",
				"audiChange": "-31",
				"audiAcc": "384488",
				"scrnCnt": "682",
				"showCnt": "1676"
			},
			{
				"rnum": "2",
				"rank": "2",
				"rankInten": "-1",
				"rankOldAndNew": "OLD",
				"movieCd": "20170942",
				"movieNm": "인랑",
				"openDt": "2018-07-25",
				"salesAmt": "424181000",
				"salesShare": "41.2",
				"salesInten": "-725186100",
				"salesChange": "-63.1",
				"salesAcc": "6324497006",
				"audiCnt": "53845",
				"audiInten": "-75669",
				"audiChange": "-58.4",
				"audiAcc": "813160",
				"scrnCnt": "712",
				"showCnt": "2501"
			},
			{
				"rnum": "3",
				"rank": "3",
				"rankInten": "0",
				"rankOldAndNew": "OLD",
				"movieCd": "20185341",
				"movieNm": "마녀",
				"openDt": "2018-06-27",
				"salesAmt": "89940400",
				"salesShare": "8.7",
				"salesInten": "-35717700",
				"salesChange": "-28.4",
				"salesAcc": "27126862863",
				"audiCnt": "10961",
				"audiInten": "-3117",
				"audiChange": "-22.1",
				"audiAcc": "3174879",
				"scrnCnt": "265",
				"showCnt": "450"
			},
			{
				"rnum": "4",
				"rank": "4",
				"rankInten": "0",
				"rankOldAndNew": "NEW",
				"movieCd": "20186202",
				"movieNm": "신과함께-인과 연",
				"openDt": "2018-08-01",
				"salesAmt": "36423000",
				"salesShare": "3.5",
				"salesInten": "36423000",
				"salesChange": "100",
				"salesAcc": "140382100",
				"audiCnt": "4005",
				"audiInten": "4005",
				"audiChange": "100",
				"audiAcc": "15718",
				"scrnCnt": "14",
				"showCnt": "15"
			},
			{
				"rnum": "5",
				"rank": "5",
				"rankInten": "1",
				"rankOldAndNew": "OLD",
				"movieCd": "20186501",
				"movieNm": "극장판 헬로카봇 : 백악기 시대",
				"openDt": "2018-08-01",
				"salesAmt": "8201000",
				"salesShare": "0.8",
				"salesInten": "3377000",
				"salesChange": "70",
				"salesAcc": "44713000",
				"audiCnt": "902",
				"audiInten": "500",
				"audiChange": "124.4",
				"audiAcc": "4262",
				"scrnCnt": "5",
				"showCnt": "5"
			},
			{
				"rnum": "6",
				"rank": "6",
				"rankInten": "-2",
				"rankOldAndNew": "OLD",
				"movieCd": "20187682",
				"movieNm": "해적왕 작스톰",
				"openDt": "2018-07-25",
				"salesAmt": "3662200",
				"salesShare": "0.4",
				"salesInten": "-600300",
				"salesChange": "-14.1",
				"salesAcc": "39764300",
				"audiCnt": "561",
				"audiInten": "-6",
				"audiChange": "-1.1",
				"audiAcc": "4995",
				"scrnCnt": "54",
				"showCnt": "56"
			},
			{
				"rnum": "7",
				"rank": "7",
				"rankInten": "-2",
				"rankOldAndNew": "OLD",
				"movieCd": "20188042",
				"movieNm": "독전: 익스텐디드 컷",
				"openDt": "2018-07-18",
				"salesAmt": "2306000",
				"salesShare": "0.2",
				"salesInten": "-883500",
				"salesChange": "-27.7",
				"salesAcc": "841388100",
				"audiCnt": "378",
				"audiInten": "-115",
				"audiChange": "-23.3",
				"audiAcc": "137263",
				"scrnCnt": "37",
				"showCnt": "45"
			},
			{
				"rnum": "8",
				"rank": "8",
				"rankInten": "1",
				"rankOldAndNew": "OLD",
				"movieCd": "20178161",
				"movieNm": "탐정: 리턴즈",
				"openDt": "2018-06-13",
				"salesAmt": "1130000",
				"salesShare": "0.1",
				"salesInten": "335000",
				"salesChange": "42.1",
				"salesAcc": "26901997678",
				"audiCnt": "226",
				"audiInten": "67",
				"audiChange": "42.1",
				"audiAcc": "3151422",
				"scrnCnt": "7",
				"showCnt": "7"
			},
			{
				"rnum": "9",
				"rank": "9",
				"rankInten": "-2",
				"rankOldAndNew": "OLD",
				"movieCd": "20174369",
				"movieNm": "변산",
				"openDt": "2018-07-04",
				"salesAmt": "1391500",
				"salesShare": "0.1",
				"salesInten": "-1032100",
				"salesChange": "-42.6",
				"salesAcc": "4006592273",
				"audiCnt": "211",
				"audiInten": "-109",
				"audiChange": "-34.1",
				"audiAcc": "488968",
				"scrnCnt": "13",
				"showCnt": "22"
			},
			{
				"rnum": "10",
				"rank": "10",
				"rankInten": "-2",
				"rankOldAndNew": "OLD",
				"movieCd": "20172469",
				"movieNm": "허스토리",
				"openDt": "2018-06-27",
				"salesAmt": "1469600",
				"salesShare": "0.1",
				"salesInten": "5100",
				"salesChange": "0.3",
				"salesAcc": "2468960649",
				"audiCnt": "203",
				"audiInten": "6",
				"audiChange": "3",
				"audiAcc": "329026",
				"scrnCnt": "8",
				"showCnt": "14"
			}
		]
	}
}