{
	"boxOfficeResult": {
		"boxofficeType": "일별 박스오피스",
		"showRange": "20171227~20171227",
		"dailyBoxOfficeList": [
			{
				"rnum": "1",
				"rank": "1",
				"rankInten": "0",
				"rankOldAndNew": "OLD",
				"movieCd": "20150976",
				"movieNm": "신과함께-죄와 벌",
				"openDt": "2017-12-20",
				"salesAmt": "3021329100",
				"salesShare": "54.8",
				"salesInten": "-174040000",
				"salesChange": "-5.4",
				"salesAcc": "45007553919",
				"audiCnt": "495106",
				"audiInten": "65080",
				"audiChange": "15.1",
				"audiAcc": "5696686",
				"scrnCnt": "1428",
				"showCnt": "5998"
			},
			{
				"rnum": "2",
				"rank": "2",
				"rankInten": "2",
				"rankOldAndNew": "OLD",
				"movieCd": "20170590",
				"movieNm": "1987",
				"openDt": "2017-12-27",
				"salesAmt": "1973650400",
				"salesShare": "35.8",
				"salesInten": "1909449900",
				"salesChange": "2974.2",
				"salesAcc": "2277747900",
				"audiCnt": "331736",
				"audiInten": "324568",
				"audiChange": "4528",
				"audiAcc": "367067",
				"scrnCnt": "1299",
				"showCnt": "6074"
			},
			{
				"rnum": "3",
				"rank": "3",
				"rankInten": "-1",
				"rankOldAndNew": "OLD",
				"movieCd": "20170402",
				"movieNm": "강철비",
				"openDt": "2017-12-14",
				"salesAmt": "457801400",
				"salesShare": "8.3",
				"salesInten": "-309901600",
				"salesChange": "-40.4",
				"salesAcc": "29181759422",
				"audiCnt": "76078",
				"audiInten": "-27527",
				"audiChange": "-26.6",
				"audiAcc": "3665938",
				"scrnCnt": "610",
				"showCnt": "1599"
			},
			{
				"rnum": "4",
				"rank": "4",
				"rankInten": "-1",
				"rankOldAndNew": "OLD",
				"movieCd": "20174846",
				"movieNm": "뽀로로 극장판 공룡섬 대모험",
				"openDt": "2017-12-07",
				"salesAmt": "55435700",
				"salesShare": "1.0",
				"salesInten": "-27459100",
				"salesChange": "-33.1",
				"salesAcc": "5500262800",
				"audiCnt": "8384",
				"audiInten": "-3610",
				"audiChange": "-30.1",
				"audiAcc": "728124",
				"scrnCnt": "142",
				"showCnt": "170"
			},
			{
				"rnum": "5",
				"rank": "5",
				"rankInten": "0",
				"rankOldAndNew": "OLD",
				"movieCd": "20173581",
				"movieNm": "기억의 밤",
				"openDt": "2017-11-29",
				"salesAmt": "1384000",
				"salesShare": "0.0",
				"salesInten": "-880500",
				"salesChange": "-38.9",
				"salesAcc": "10645654660",
				"audiCnt": "251",
				"audiInten": "-147",
				"audiChange": "-36.9",
				"audiAcc": "1386411",
				"scrnCnt": "25",
				"showCnt": "26"
			},
			{
				"rnum": "6",
				"rank": "6",
				"rankInten": "0",
				"rankOldAndNew": "OLD",
				"movieCd": "20175830",
				"movieNm": "돌아와요 부산항애(愛)",
				"openDt": "2018-01-17",
				"salesAmt": "1972000",
				"salesShare": "0.0",
				"salesInten": "-596000",
				"salesChange": "-23.2",
				"salesAcc": "7280000",
				"audiCnt": "231",
				"audiInten": "-90",
				"audiChange": "-28",
				"audiAcc": "826",
				"scrnCnt": "2",
				"showCnt": "2"
			},
			{
				"rnum": "7",
				"rank": "7",
				"rankInten": "1",
				"rankOldAndNew": "OLD",
				"movieCd": "20100268",
				"movieNm": "별들의 고향 ",
				"openDt": "1974-04-26",
				"salesAmt": "456000",
				"salesShare": "0.0",
				"salesInten": "-92000",
				"salesChange": "-16.8",
				"salesAcc": "8068000",
				"audiCnt": "228",
				"audiInten": "-46",
				"audiChange": "-16.8",
				"audiAcc": "3361",
				"scrnCnt": "1",
				"showCnt": "5"
			},
			{
				"rnum": "8",
				"rank": "8",
				"rankInten": "0",
				"rankOldAndNew": "NEW",
				"movieCd": "19618005",
				"movieNm": "언니는 말괄량이",
				"openDt": " ",
				"salesAmt": "238000",
				"salesShare": "0.0",
				"salesInten": "238000",
				"salesChange": "100",
				"salesAcc": "6902000",
				"audiCnt": "119",
				"audiInten": "119",
				"audiChange": "100",
				"audiAcc": "4186",
				"scrnCnt": "1",
				"showCnt": "4"
			},
			{
				"rnum": "9",
				"rank": "9",
				"rankInten": "0",
				"rankOldAndNew": "NEW",
				"movieCd": "20178647",
				"movieNm": "땐뽀걸즈",
				"openDt": "2017-09-27",
				"salesAmt": "1153000",
				"salesShare": "0.0",
				"salesInten": "1153000",
				"salesChange": "100",
				"salesAcc": "55753300",
				"audiCnt": "116",
				"audiInten": "116",
				"audiChange": "100",
				"audiAcc": "6996",
				"scrnCnt": "1",
				"showCnt": "1"
			},
			{
				"rnum": "10",
				"rank": "10",
				"rankInten": "5",
				"rankOldAndNew": "OLD",
				"movieCd": "20174601",
				"movieNm": "초행",
				"openDt": "2017-12-07",
				"salesAmt": "834500",
				"salesShare": "0.0",
				"salesInten": "210500",
				"salesChange": "33.7",
				"salesAcc": "49328000",
				"audiCnt": "110",
				"audiInten": "26",
				"audiChange": "31",
				"audiAcc": "6352",
				"scrnCnt": "17",
				"showCnt": "22"
			}
		]
	}
}