{
	"boxOfficeResult": {
		"boxofficeType": "일별 박스오피스",
		"showRange": "20171118~20171118",
		"dailyBoxOfficeList": [
			{
				"rnum": "1",
				"rank": "1",
				"rankInten": "0",
				"rankOldAndNew": "OLD",
				"movieCd": "20168754",
				"movieNm": "7호실",
				"openDt": "2017-11-15",
				"salesAmt": "545121779",
				"salesShare": "49.7",
				"salesInten": "239515921",
				"salesChange": "78.4",
				"salesAcc": "1681059237",
				"audiCnt": "65969",
				"audiInten": "27502",
				"audiChange": "71.5",
				"audiAcc": "218805",
				"scrnCnt": "556",
				"showCnt": "2527"
			},
			{
				"rnum": "2",
				"rank": "2",
				"rankInten": "0",
				"rankOldAndNew": "OLD",
				"movieCd": "20172603",
				"movieNm": "부라더",
				"openDt": "2017-11-02",
				"salesAmt": "227629400",
				"salesShare": "20.7",
				"salesInten": "102982100",
				"salesChange": "82.6",
				"salesAcc": "11297230298",
				"audiCnt": "28393",
				"audiInten": "11875",
				"audiChange": "71.9",
				"audiAcc": "1426285",
				"scrnCnt": "479",
				"showCnt": "1057"
			},
			{
				"rnum": "3",
				"rank": "3",
				"rankInten": "0",
				"rankOldAndNew": "OLD",
				"movieCd": "20172742",
				"movieNm": "범죄도시",
				"openDt": "2017-10-03",
				"salesAmt": "228801000",
				"salesShare": "20.8",
				"salesInten": "109453400",
				"salesChange": "91.7",
				"salesAcc": "55582675449",
				"audiCnt": "26516",
				"audiInten": "12478",
				"audiChange": "88.9",
				"audiAcc": "6789375",
				"scrnCnt": "375",
				"showCnt": "750"
			},
			{
				"rnum": "4",
				"rank": "4",
				"rankInten": "1",
				"rankOldAndNew": "OLD",
				"movieCd": "20175441",
				"movieNm": "채비",
				"openDt": "2017-11-09",
				"salesAmt": "50492800",
				"salesShare": "4.6",
				"salesInten": "17831800",
				"salesChange": "54.6",
				"salesAcc": "901902864",
				"audiCnt": "6519",
				"audiInten": "1986",
				"audiChange": "43.8",
				"audiAcc": "123370",
				"scrnCnt": "152",
				"showCnt": "220"
			},
			{
				"rnum": "5",
				"rank": "5",
				"rankInten": "1",
				"rankOldAndNew": "OLD",
				"movieCd": "20161681",
				"movieNm": "미옥",
				"openDt": "2017-11-09",
				"salesAmt": "10752500",
				"salesShare": "1.0",
				"salesInten": "178100",
				"salesChange": "1.7",
				"salesAcc": "1868829564",
				"audiCnt": "1439",
				"audiInten": "45",
				"audiChange": "3.2",
				"audiAcc": "234583",
				"scrnCnt": "111",
				"showCnt": "155"
			},
			{
				"rnum": "6",
				"rank": "6",
				"rankInten": "1",
				"rankOldAndNew": "OLD",
				"movieCd": "20169643",
				"movieNm": "침묵",
				"openDt": "2017-11-02",
				"salesAmt": "8822000",
				"salesShare": "0.8",
				"salesInten": "1200300",
				"salesChange": "15.7",
				"salesAcc": "3901430664",
				"audiCnt": "1134",
				"audiInten": "169",
				"audiChange": "17.5",
				"audiAcc": "490224",
				"scrnCnt": "61",
				"showCnt": "72"
			},
			{
				"rnum": "7",
				"rank": "7",
				"rankInten": "1",
				"rankOldAndNew": "OLD",
				"movieCd": "20175208",
				"movieNm": "뷰티풀 투모로우",
				"openDt": "2017-10-26",
				"salesAmt": "5863400",
				"salesShare": "0.5",
				"salesInten": "1576900",
				"salesChange": "36.8",
				"salesAcc": "515659300",
				"audiCnt": "724",
				"audiInten": "172",
				"audiChange": "31.2",
				"audiAcc": "58509",
				"scrnCnt": "8",
				"showCnt": "11"
			},
			{
				"rnum": "8",
				"rank": "8",
				"rankInten": "9",
				"rankOldAndNew": "OLD",
				"movieCd": "20171817",
				"movieNm": "넛잡 2",
				"openDt": "2017-10-03",
				"salesAmt": "2872500",
				"salesShare": "0.3",
				"salesInten": "2020500",
				"salesChange": "237.1",
				"salesAcc": "3052831100",
				"audiCnt": "401",
				"audiInten": "256",
				"audiChange": "176.6",
				"audiAcc": "409128",
				"scrnCnt": "11",
				"showCnt": "19"
			},
			{
				"rnum": "9",
				"rank": "9",
				"rankInten": "0",
				"rankOldAndNew": "OLD",
				"movieCd": "20173932",
				"movieNm": "로마서 8:37",
				"openDt": "2017-11-16",
				"salesAmt": "3031000",
				"salesShare": "0.3",
				"salesInten": "-568000",
				"salesChange": "-15.8",
				"salesAcc": "17503500",
				"audiCnt": "366",
				"audiInten": "-63",
				"audiChange": "-14.7",
				"audiAcc": "2206",
				"scrnCnt": "42",
				"showCnt": "54"
			},
			{
				"rnum": "10",
				"rank": "10",
				"rankInten": "1",
				"rankOldAndNew": "OLD",
				"movieCd": "20174142",
				"movieNm": "아이 캔 스피크",
				"openDt": "2017-09-21",
				"salesAmt": "1690000",
				"salesShare": "0.2",
				"salesInten": "232000",
				"salesChange": "15.9",
				"salesAcc": "25483893186",
				"audiCnt": "307",
				"audiInten": "26",
				"audiChange": "9.3",
				"audiAcc": "3271830",
				"scrnCnt": "3",
				"showCnt": "3"
			}
		]
	}
}