{
	"boxOfficeResult": {
		"boxofficeType": "일별 박스오피스",
		"showRange": "20170623~20170623",
		"dailyBoxOfficeList": [
			{
				"rnum": "1",
				"rank": "1",
				"rankInten": "0",
				"rankOldAndNew": "OLD",
				"movieCd": "20166384",
				"movieNm": "하루",
				"openDt": "2017-06-15",
				"salesAmt": "367430025",
				"salesShare": "59.1",
				"salesInten": "79892625",
				"salesChange": "27.8",
				"salesAcc": "6488852643",
				"audiCnt": "44572",
				"audiInten": "5994",
				"audiChange": "15.5",
				"audiAcc": "807223",
				"scrnCnt": "594",
				"showCnt": "2022"
			},
			{
				"rnum": "2",
				"rank": "2",
				"rankInten": "0",
				"rankOldAndNew": "OLD",
				"movieCd": "20162343",
				"movieNm": "악녀",
				"openDt": "2017-06-08",
				"salesAmt": "172237539",
				"salesShare": "27.7",
				"salesInten": "45634039",
				"salesChange": "36",
				"salesAcc": "8497735209",
				"audiCnt": "20652",
				"audiInten": "3522",
				"audiChange": "20.6",
				"audiAcc": "1052689",
				"scrnCnt": "451",
				"showCnt": "1050"
			},
			{
				"rnum": "3",
				"rank": "3",
				"rankInten": "0",
				"rankOldAndNew": "OLD",
				"movieCd": "20174602",
				"movieNm": "노무현입니다",
				"openDt": "2017-05-25",
				"salesAmt": "56668500",
				"salesShare": "9.1",
				"salesInten": "11250000",
				"salesChange": "24.8",
				"salesAcc": "13909929712",
				"audiCnt": "7145",
				"audiInten": "718",
				"audiChange": "11.2",
				"audiAcc": "1768845",
				"scrnCnt": "300",
				"showCnt": "529"
			},
			{
				"rnum": "4",
				"rank": "4",
				"rankInten": "14",
				"rankOldAndNew": "OLD",
				"movieCd": "20178982",
				"movieNm": "박열",
				"openDt": "2017-06-28",
				"salesAmt": "5614500",
				"salesShare": "0.9",
				"salesInten": "5204500",
				"salesChange": "1269.4",
				"salesAcc": "128038500",
				"audiCnt": "582",
				"audiInten": "500",
				"audiChange": "609.8",
				"audiAcc": "15937",
				"scrnCnt": "3",
				"showCnt": "5"
			},
			{
				"rnum": "5",
				"rank": "5",
				"rankInten": "0",
				"rankOldAndNew": "OLD",
				"movieCd": "20164844",
				"movieNm": "불한당: 나쁜 놈들의 세상",
				"openDt": "2017-05-17",
				"salesAmt": "4406500",
				"salesShare": "0.7",
				"salesInten": "-1332000",
				"salesChange": "-23.2",
				"salesAcc": "7484178725",
				"audiCnt": "471",
				"audiInten": "-310",
				"audiChange": "-39.7",
				"audiAcc": "927787",
				"scrnCnt": "6",
				"showCnt": "10"
			},
			{
				"rnum": "6",
				"rank": "6",
				"rankInten": "0",
				"rankOldAndNew": "OLD",
				"movieCd": "20162722",
				"movieNm": "보안관",
				"openDt": "2017-05-03",
				"salesAmt": "1800000",
				"salesShare": "0.3",
				"salesInten": "-2205000",
				"salesChange": "-55.1",
				"salesAcc": "20838585409",
				"audiCnt": "450",
				"audiInten": "-315",
				"audiChange": "-41.2",
				"audiAcc": "2587648",
				"scrnCnt": "2",
				"showCnt": "4"
			},
			{
				"rnum": "7",
				"rank": "7",
				"rankInten": "0",
				"rankOldAndNew": "OLD",
				"movieCd": "20160483",
				"movieNm": "꿈의 제인",
				"openDt": "2017-05-31",
				"salesAmt": "2593000",
				"salesShare": "0.4",
				"salesInten": "272000",
				"salesChange": "11.7",
				"salesAcc": "166803000",
				"audiCnt": "307",
				"audiInten": "9",
				"audiChange": "3",
				"audiAcc": "20287",
				"scrnCnt": "19",
				"showCnt": "24"
			},
			{
				"rnum": "8",
				"rank": "8",
				"rankInten": "1",
				"rankOldAndNew": "OLD",
				"movieCd": "20174281",
				"movieNm": "파란나비효과",
				"openDt": "2017-06-22",
				"salesAmt": "2029100",
				"salesShare": "0.3",
				"salesInten": "298600",
				"salesChange": "17.3",
				"salesAcc": "20972600",
				"audiCnt": "278",
				"audiInten": "18",
				"audiChange": "6.9",
				"audiAcc": "2942",
				"scrnCnt": "40",
				"showCnt": "51"
			},
			{
				"rnum": "9",
				"rank": "9",
				"rankInten": "0",
				"rankOldAndNew": "NEW",
				"movieCd": "19560023",
				"movieNm": "격퇴",
				"openDt": "1956-04-04",
				"salesAmt": "379000",
				"salesShare": "0.1",
				"salesInten": "379000",
				"salesChange": "100",
				"salesAcc": "379000",
				"audiCnt": "246",
				"audiInten": "246",
				"audiChange": "100",
				"audiAcc": "246",
				"scrnCnt": "1",
				"showCnt": "3"
			},
			{
				"rnum": "10",
				"rank": "10",
				"rankInten": "-6",
				"rankOldAndNew": "OLD",
				"movieCd": "20169348",
				"movieNm": "대립군",
				"openDt": "2017-05-31",
				"salesAmt": "1524500",
				"salesShare": "0.2",
				"salesInten": "-4165000",
				"salesChange": "-73.2",
				"salesAcc": "6251121802",
				"audiCnt": "216",
				"audiInten": "-683",
				"audiChange": "-76",
				"audiAcc": "833226",
				"scrnCnt": "17",
				"showCnt": "17"
			}
		]
	}
}