{
	"boxOfficeResult": {
		"boxofficeType": "일별 박스오피스",
		"showRange": "20170521~20170521",
		"dailyBoxOfficeList": [
			{
				"rnum": "1",
				"rank": "1",
				"rankInten": "0",
				"rankOldAndNew": "OLD",
				"movieCd": "20164844",
				"movieNm": "불한당: 나쁜 놈들의 세상",
				"openDt": "2017-05-17",
				"salesAmt": "1190814900",
				"salesShare": "71.7",
				"salesInten": "-98485673",
				"salesChange": "-7.6",
				"salesAcc": "4842202745",
				"audiCnt": "138594",
				"audiInten": "-11855",
				"audiChange": "-7.9",
				"audiAcc": "589914",
				"scrnCnt": "826",
				"showCnt": "3624"
			},
			{
				"rnum": "2",
				"rank": "2",
				"rankInten": "0",
				"rankOldAndNew": "OLD",
				"movieCd": "20162722",
				"movieNm": "보안관",
				"openDt": "2017-05-03",
				"salesAmt": "415640900",
				"salesShare": "25.0",
				"salesInten": "-35169700",
				"salesChange": "-7.8",
				"salesAcc": "20264979109",
				"audiCnt": "49740",
				"audiInten": "-4616",
				"audiChange": "-8.5",
				"audiAcc": "2509467",
				"scrnCnt": "532",
				"showCnt": "1756"
			},
			{
				"rnum": "3",
				"rank": "3",
				"rankInten": "0",
				"rankOldAndNew": "OLD",
				"movieCd": "20156708",
				"movieNm": "석조저택 살인사건",
				"openDt": "2017-05-09",
				"salesAmt": "27748300",
				"salesShare": "1.7",
				"salesInten": "-4546100",
				"salesChange": "-14.1",
				"salesAcc": "2772559986",
				"audiCnt": "3540",
				"audiInten": "-510",
				"audiChange": "-12.6",
				"audiAcc": "346044",
				"scrnCnt": "207",
				"showCnt": "291"
			},
			{
				"rnum": "4",
				"rank": "4",
				"rankInten": "1",
				"rankOldAndNew": "OLD",
				"movieCd": "20167829",
				"movieNm": "마차 타고 고래고래",
				"openDt": "2017-05-18",
				"salesAmt": "8944000",
				"salesShare": "0.5",
				"salesInten": "-1879000",
				"salesChange": "-17.4",
				"salesAcc": "57690500",
				"audiCnt": "1041",
				"audiInten": "-205",
				"audiChange": "-16.5",
				"audiAcc": "6760",
				"scrnCnt": "83",
				"showCnt": "109"
			},
			{
				"rnum": "5",
				"rank": "5",
				"rankInten": "2",
				"rankOldAndNew": "OLD",
				"movieCd": "20173301",
				"movieNm": "서서평, 천천히 평온하게",
				"openDt": "2017-04-26",
				"salesAmt": "5303500",
				"salesShare": "0.3",
				"salesInten": "-3096100",
				"salesChange": "-36.9",
				"salesAcc": "697662500",
				"audiCnt": "743",
				"audiInten": "-275",
				"audiChange": "-27",
				"audiAcc": "93607",
				"scrnCnt": "26",
				"showCnt": "34"
			},
			{
				"rnum": "6",
				"rank": "6",
				"rankInten": "-2",
				"rankOldAndNew": "OLD",
				"movieCd": "20173061",
				"movieNm": "슈퍼 빼꼼: 스파이 대작전",
				"openDt": "2017-05-03",
				"salesAmt": "3329500",
				"salesShare": "0.2",
				"salesInten": "-9057000",
				"salesChange": "-73.1",
				"salesAcc": "690244900",
				"audiCnt": "474",
				"audiInten": "-1292",
				"audiChange": "-73.2",
				"audiAcc": "96213",
				"scrnCnt": "21",
				"showCnt": "26"
			},
			{
				"rnum": "7",
				"rank": "7",
				"rankInten": "-1",
				"rankOldAndNew": "OLD",
				"movieCd": "20161726",
				"movieNm": "임금님의 사건수첩",
				"openDt": "2017-04-26",
				"salesAmt": "3056500",
				"salesShare": "0.2",
				"salesInten": "-4959700",
				"salesChange": "-61.9",
				"salesAcc": "12632234223",
				"audiCnt": "394",
				"audiInten": "-771",
				"audiChange": "-66.2",
				"audiAcc": "1631220",
				"scrnCnt": "19",
				"showCnt": "27"
			},
			{
				"rnum": "8",
				"rank": "8",
				"rankInten": "2",
				"rankOldAndNew": "OLD",
				"movieCd": "20174165",
				"movieNm": "극장판 또봇: 로봇군단의 습격",
				"openDt": "2017-04-27",
				"salesAmt": "2031100",
				"salesShare": "0.1",
				"salesInten": "414600",
				"salesChange": "25.6",
				"salesAcc": "1086599800",
				"audiCnt": "244",
				"audiInten": "45",
				"audiChange": "22.6",
				"audiAcc": "141285",
				"scrnCnt": "6",
				"showCnt": "6"
			},
			{
				"rnum": "9",
				"rank": "9",
				"rankInten": "1",
				"rankOldAndNew": "OLD",
				"movieCd": "20164041",
				"movieNm": "고려 아리랑: 천산의 디바",
				"openDt": "2017-05-25",
				"salesAmt": "2505700",
				"salesShare": "0.2",
				"salesInten": "316700",
				"salesChange": "14.5",
				"salesAcc": "8237200",
				"audiCnt": "230",
				"audiInten": "31",
				"audiChange": "15.6",
				"audiAcc": "998",
				"scrnCnt": "1",
				"showCnt": "1"
			},
			{
				"rnum": "10",
				"rank": "10",
				"rankInten": "0",
				"rankOldAndNew": "NEW",
				"movieCd": "19550028",
				"movieNm": "미망인",
				"openDt": "1955-12-10",
				"salesAmt": "339000",
				"salesShare": "0.0",
				"salesInten": "339000",
				"salesChange": "100",
				"salesAcc": "2652000",
				"audiCnt": "113",
				"audiInten": "113",
				"audiChange": "100",
				"audiAcc": "970",
				"scrnCnt": "1",
				"showCnt": "2"
			}
		]
	}
}