{
	"boxOfficeResult": {
		"boxofficeType": "일별 박스오피스",
		"showRange": "20171201~20171201",
		"dailyBoxOfficeList": [
			{
				"rnum": "1",
				"rank": "1",
				"rankInten": "0",
				"rankOldAndNew": "OLD",
				"movieCd": "20178581",
				"movieNm": "오리엔트 특급 살인",
				"openDt": "2017-11-29",
				"salesAmt": "578369155",
				"salesShare": "54.8",
				"salesInten": "137352755",
				"salesChange": "31.1",
				"salesAcc": "1585473455",
				"audiCnt": "70962",
				"audiInten": "10198",
				"audiChange": "16.8",
				"audiAcc": "227167",
				"scrnCnt": "663",
				"showCnt": "2914"
			},
			{
				"rnum": "2",
				"rank": "2",
				"rankInten": "1",
				"rankOldAndNew": "OLD",
				"movieCd": "20040695",
				"movieNm": "이프 온리",
				"openDt": "2004-10-29",
				"salesAmt": "103468400",
				"salesShare": "9.8",
				"salesInten": "37972100",
				"salesChange": "58",
				"salesAcc": "5772407200",
				"audiCnt": "12135",
				"audiInten": "3239",
				"audiChange": "36.4",
				"audiAcc": "894921",
				"scrnCnt": "145",
				"showCnt": "643"
			},
			{
				"rnum": "3",
				"rank": "3",
				"rankInten": "-1",
				"rankOldAndNew": "OLD",
				"movieCd": "20168221",
				"movieNm": "저스티스 리그",
				"openDt": "2017-11-15",
				"salesAmt": "92376600",
				"salesShare": "8.7",
				"salesInten": "15429100",
				"salesChange": "20.1",
				"salesAcc": "14033122795",
				"audiCnt": "11719",
				"audiInten": "894",
				"audiChange": "8.3",
				"audiAcc": "1710469",
				"scrnCnt": "416",
				"showCnt": "878"
			},
			{
				"rnum": "4",
				"rank": "4",
				"rankInten": "0",
				"rankOldAndNew": "OLD",
				"movieCd": "20179942",
				"movieNm": "러빙 빈센트",
				"openDt": "2017-11-09",
				"salesAmt": "70446300",
				"salesShare": "6.7",
				"salesInten": "9897300",
				"salesChange": "16.3",
				"salesAcc": "1960679200",
				"audiCnt": "8440",
				"audiInten": "147",
				"audiChange": "1.8",
				"audiAcc": "247853",
				"scrnCnt": "185",
				"showCnt": "392"
			},
			{
				"rnum": "5",
				"rank": "5",
				"rankInten": "0",
				"rankOldAndNew": "OLD",
				"movieCd": "20175121",
				"movieNm": "토르: 라그나로크",
				"openDt": "2017-10-25",
				"salesAmt": "62549500",
				"salesShare": "5.9",
				"salesInten": "15917700",
				"salesChange": "34.1",
				"salesAcc": "38776855695",
				"audiCnt": "7879",
				"audiInten": "1372",
				"audiChange": "21.1",
				"audiAcc": "4797392",
				"scrnCnt": "228",
				"showCnt": "349"
			},
			{
				"rnum": "6",
				"rank": "6",
				"rankInten": "0",
				"rankOldAndNew": "OLD",
				"movieCd": "20174622",
				"movieNm": "해피 데스데이",
				"openDt": "2017-11-08",
				"salesAmt": "46438673",
				"salesShare": "4.4",
				"salesInten": "9856673",
				"salesChange": "26.9",
				"salesAcc": "10803332728",
				"audiCnt": "6029",
				"audiInten": "996",
				"audiChange": "19.8",
				"audiAcc": "1357033",
				"scrnCnt": "270",
				"showCnt": "515"
			},
			{
				"rnum": "7",
				"rank": "7",
				"rankInten": "2",
				"rankOldAndNew": "OLD",
				"movieCd": "20080349",
				"movieNm": "버킷 리스트:죽기전에 꼭 하고싶은것들",
				"openDt": "2008-04-09",
				"salesAmt": "8888400",
				"salesShare": "0.8",
				"salesInten": "2770900",
				"salesChange": "45.3",
				"salesAcc": "1878730700",
				"audiCnt": "1246",
				"audiInten": "363",
				"audiChange": "41.1",
				"audiAcc": "282717",
				"scrnCnt": "57",
				"showCnt": "99"
			},
			{
				"rnum": "8",
				"rank": "8",
				"rankInten": "-1",
				"rankOldAndNew": "OLD",
				"movieCd": "20174778",
				"movieNm": "하이큐!! 재능과 센스",
				"openDt": "2017-11-15",
				"salesAmt": "7262000",
				"salesShare": "0.7",
				"salesInten": "-9950000",
				"salesChange": "-57.8",
				"salesAcc": "210181500",
				"audiCnt": "965",
				"audiInten": "-1565",
				"audiChange": "-61.9",
				"audiAcc": "29701",
				"scrnCnt": "44",
				"showCnt": "60"
			},
			{
				"rnum": "9",
				"rank": "9",
				"rankInten": "1",
				"rankOldAndNew": "OLD",
				"movieCd": "20174073",
				"movieNm": "빅 배드 폭스",
				"openDt": "2017-11-30",
				"salesAmt": "6190000",
				"salesShare": "0.6",
				"salesInten": "317000",
				"salesChange": "5.4",
				"salesAcc": "17223000",
				"audiCnt": "887",
				"audiInten": "59",
				"audiChange": "7.1",
				"audiAcc": "2360",
				"scrnCnt": "110",
				"showCnt": "115"
			},
			{
				"rnum": "10",
				"rank": "10",
				"rankInten": "3",
				"rankOldAndNew": "OLD",
				"movieCd": "20175811",
				"movieNm": "토마스와 친구들: 그레이트 레이스",
				"openDt": "2017-11-30",
				"salesAmt": "4780700",
				"salesShare": "0.5",
				"salesInten": "585300",
				"salesChange": "14",
				"salesAcc": "12086100",
				"audiCnt": "653",
				"audiInten": "17",
				"audiChange": "2.7",
				"audiAcc": "1640",
				"scrnCnt": "127",
				"showCnt": "137"
			}
		]
	}
}