{
	"boxOfficeResult": {
		"boxofficeType": "일별 박스오피스",
		"showRange": "20171130~20171130",
		"dailyBoxOfficeList": [
			{
				"rnum": "1",
				"rank": "1",
				"rankInten": "0",
				"rankOldAndNew": "OLD",
				"movieCd": "20165748",
				"movieNm": "꾼",
				"openDt": "2017-11-22",
				"salesAmt": "898433200",
				"salesShare": "52.1",
				"salesInten": "-276887400",
				"salesChange": "-23.6",
				"salesAcc": "17818901348",
				"audiCnt": "124399",
				"audiInten": "-77124",
				"audiChange": "-38.3",
				"audiAcc": "2324334",
				"scrnCnt": "944",
				"showCnt": "4456"
			},
			{
				"rnum": "2",
				"rank": "2",
				"rankInten": "0",
				"rankOldAndNew": "OLD",
				"movieCd": "20173581",
				"movieNm": "기억의 밤",
				"openDt": "2017-11-29",
				"salesAmt": "502241400",
				"salesShare": "29.1",
				"salesInten": "-59016800",
				"salesChange": "-10.5",
				"salesAcc": "1106452900",
				"audiCnt": "69328",
				"audiInten": "-27917",
				"audiChange": "-28.7",
				"audiAcc": "173709",
				"scrnCnt": "714",
				"showCnt": "3291"
			},
			{
				"rnum": "3",
				"rank": "3",
				"rankInten": "0",
				"rankOldAndNew": "OLD",
				"movieCd": "20161762",
				"movieNm": "반드시 잡는다",
				"openDt": "2017-11-29",
				"salesAmt": "264702100",
				"salesShare": "15.4",
				"salesInten": "-91143600",
				"salesChange": "-25.6",
				"salesAcc": "681372800",
				"audiCnt": "37426",
				"audiInten": "-22481",
				"audiChange": "-37.5",
				"audiAcc": "104600",
				"scrnCnt": "554",
				"showCnt": "2489"
			},
			{
				"rnum": "4",
				"rank": "4",
				"rankInten": "0",
				"rankOldAndNew": "NEW",
				"movieCd": "20174846",
				"movieNm": "뽀로로 극장판 공룡섬 대모험",
				"openDt": "2017-12-07",
				"salesAmt": "15200000",
				"salesShare": "0.9",
				"salesInten": "15200000",
				"salesChange": "100",
				"salesAcc": "22840000",
				"audiCnt": "1900",
				"audiInten": "1900",
				"audiChange": "100",
				"audiAcc": "2942",
				"scrnCnt": "9",
				"showCnt": "9"
			},
			{
				"rnum": "5",
				"rank": "5",
				"rankInten": "1",
				"rankOldAndNew": "OLD",
				"movieCd": "20172742",
				"movieNm": "범죄도시",
				"openDt": "2017-10-03",
				"salesAmt": "6612000",
				"salesShare": "0.4",
				"salesInten": "-1673900",
				"salesChange": "-20.2",
				"salesAcc": "56263606249",
				"audiCnt": "912",
				"audiInten": "-383",
				"audiChange": "-29.6",
				"audiAcc": "6873292",
				"scrnCnt": "51",
				"showCnt": "70"
			},
			{
				"rnum": "6",
				"rank": "6",
				"rankInten": "-2",
				"rankOldAndNew": "OLD",
				"movieCd": "20175441",
				"movieNm": "채비",
				"openDt": "2017-11-09",
				"salesAmt": "4655500",
				"salesShare": "0.3",
				"salesInten": "-5974500",
				"salesChange": "-56.2",
				"salesAcc": "1174621664",
				"audiCnt": "851",
				"audiInten": "-1184",
				"audiChange": "-58.2",
				"audiAcc": "163533",
				"scrnCnt": "40",
				"showCnt": "47"
			},
			{
				"rnum": "7",
				"rank": "7",
				"rankInten": "23",
				"rankOldAndNew": "OLD",
				"movieCd": "20174663",
				"movieNm": "돌아온다",
				"openDt": "2017-12-07",
				"salesAmt": "6170000",
				"salesShare": "0.4",
				"salesInten": "5321000",
				"salesChange": "626.7",
				"salesAcc": "7019000",
				"audiCnt": "822",
				"audiInten": "737",
				"audiChange": "867.1",
				"audiAcc": "907",
				"scrnCnt": "3",
				"showCnt": "3"
			},
			{
				"rnum": "8",
				"rank": "8",
				"rankInten": "5",
				"rankOldAndNew": "OLD",
				"movieCd": "20163906",
				"movieNm": "아들에게 가는 길",
				"openDt": "2017-11-30",
				"salesAmt": "3601900",
				"salesShare": "0.2",
				"salesInten": "1104900",
				"salesChange": "44.2",
				"salesAcc": "11971400",
				"audiCnt": "652",
				"audiInten": "373",
				"audiChange": "133.7",
				"audiAcc": "1697",
				"scrnCnt": "45",
				"showCnt": "70"
			},
			{
				"rnum": "9",
				"rank": "9",
				"rankInten": "-1",
				"rankOldAndNew": "OLD",
				"movieCd": "20172603",
				"movieNm": "부라더",
				"openDt": "2017-11-02",
				"salesAmt": "2020500",
				"salesShare": "0.1",
				"salesInten": "-1113500",
				"salesChange": "-35.5",
				"salesAcc": "11767035198",
				"audiCnt": "369",
				"audiInten": "-271",
				"audiChange": "-42.3",
				"audiAcc": "1490050",
				"scrnCnt": "14",
				"showCnt": "18"
			},
			{
				"rnum": "10",
				"rank": "10",
				"rankInten": "-5",
				"rankOldAndNew": "OLD",
				"movieCd": "20168754",
				"movieNm": "7호실",
				"openDt": "2017-11-15",
				"salesAmt": "2497100",
				"salesShare": "0.1",
				"salesInten": "-12266400",
				"salesChange": "-83.1",
				"salesAcc": "2653200039",
				"audiCnt": "351",
				"audiInten": "-1662",
				"audiChange": "-82.6",
				"audiAcc": "343990",
				"scrnCnt": "21",
				"showCnt": "33"
			}
		]
	}
}