{
	"boxOfficeResult": {
		"boxofficeType": "일별 박스오피스",
		"showRange": "20180711~20180711",
		"dailyBoxOfficeList": [
			{
				"rnum": "1",
				"rank": "1",
				"rankInten": "0",
				"rankOldAndNew": "OLD",
				"movieCd": "20180522",
				"movieNm": "앤트맨과 와스프",
				"openDt": "2018-07-04",
				"salesAmt": "1339303000",
				"salesShare": "62.1",
				"salesInten": "-335563500",
				"salesChange": "-20",
				"salesAcc": "27935482481",
				"audiCnt": "163809",
				"audiInten": "-40259",
				"audiChange": "-19.7",
				"audiAcc": "3186536",
				"scrnCnt": "1391",
				"showCnt": "7544"
			},
			{
				"rnum": "2",
				"rank": "2",
				"rankInten": "18",
				"rankOldAndNew": "OLD",
				"movieCd": "20181443",
				"movieNm": "스카이스크래퍼",
				"openDt": "2018-07-11",
				"salesAmt": "632336000",
				"salesShare": "29.3",
				"salesInten": "629978000",
				"salesChange": "26716.6",
				"salesAcc": "642308000",
				"audiCnt": "78615",
				"audiInten": "78353",
				"audiChange": "29905.7",
				"audiAcc": "79723",
				"scrnCnt": "808",
				"showCnt": "4166"
			},
			{
				"rnum": "3",
				"rank": "3",
				"rankInten": "0",
				"rankOldAndNew": "NEW",
				"movieCd": "20182564",
				"movieNm": "오늘 밤, 로맨스 극장에서",
				"openDt": "2018-07-11",
				"salesAmt": "36438800",
				"salesShare": "1.7",
				"salesInten": "36438800",
				"salesChange": "100",
				"salesAcc": "77378700",
				"audiCnt": "4552",
				"audiInten": "4552",
				"audiChange": "100",
				"audiAcc": "9002",
				"scrnCnt": "155",
				"showCnt": "569"
			},
			{
				"rnum": "4",
				"rank": "4",
				"rankInten": "-2",
				"rankOldAndNew": "OLD",
				"movieCd": "20184845",
				"movieNm": "미드나잇 선",
				"openDt": "2018-06-21",
				"salesAmt": "36395500",
				"salesShare": "1.7",
				"salesInten": "-20071100",
				"salesChange": "-35.5",
				"salesAcc": "2000215300",
				"audiCnt": "4425",
				"audiInten": "-2617",
				"audiChange": "-37.2",
				"audiAcc": "236001",
				"scrnCnt": "99",
				"showCnt": "202"
			},
			{
				"rnum": "5",
				"rank": "5",
				"rankInten": "0",
				"rankOldAndNew": "OLD",
				"movieCd": "20185001",
				"movieNm": "빅샤크: 매직체인지",
				"openDt": "2018-06-27",
				"salesAmt": "16129300",
				"salesShare": "0.7",
				"salesInten": "3441000",
				"salesChange": "27.1",
				"salesAcc": "764790700",
				"audiCnt": "2861",
				"audiInten": "710",
				"audiChange": "33",
				"audiAcc": "102692",
				"scrnCnt": "91",
				"showCnt": "103"
			},
			{
				"rnum": "6",
				"rank": "6",
				"rankInten": "-3",
				"rankOldAndNew": "OLD",
				"movieCd": "20184721",
				"movieNm": "시카리오: 데이 오브 솔다도",
				"openDt": "2018-06-27",
				"salesAmt": "15448200",
				"salesShare": "0.7",
				"salesInten": "-10569700",
				"salesChange": "-40.6",
				"salesAcc": "1831707100",
				"audiCnt": "1923",
				"audiInten": "-1211",
				"audiChange": "-38.6",
				"audiAcc": "217370",
				"scrnCnt": "66",
				"showCnt": "136"
			},
			{
				"rnum": "7",
				"rank": "7",
				"rankInten": "-1",
				"rankOldAndNew": "OLD",
				"movieCd": "20179086",
				"movieNm": "쥬라기 월드: 폴른 킹덤",
				"openDt": "2018-06-06",
				"salesAmt": "7275100",
				"salesShare": "0.3",
				"salesInten": "-8445400",
				"salesChange": "-53.7",
				"salesAcc": "49677851737",
				"audiCnt": "948",
				"audiInten": "-1093",
				"audiChange": "-53.6",
				"audiAcc": "5649918",
				"scrnCnt": "57",
				"showCnt": "88"
			},
			{
				"rnum": "8",
				"rank": "8",
				"rankInten": "-4",
				"rankOldAndNew": "OLD",
				"movieCd": "20184903",
				"movieNm": "오션스8",
				"openDt": "2018-06-13",
				"salesAmt": "7664700",
				"salesShare": "0.4",
				"salesInten": "-11818400",
				"salesChange": "-60.7",
				"salesAcc": "11666073766",
				"audiCnt": "922",
				"audiInten": "-1513",
				"audiChange": "-62.1",
				"audiAcc": "1331862",
				"scrnCnt": "30",
				"showCnt": "54"
			},
			{
				"rnum": "9",
				"rank": "9",
				"rankInten": "0",
				"rankOldAndNew": "NEW",
				"movieCd": "20183361",
				"movieNm": "인크레더블 2",
				"openDt": "2018-07-18",
				"salesAmt": "8736000",
				"salesShare": "0.4",
				"salesInten": "8736000",
				"salesChange": "100",
				"salesAcc": "17472000",
				"audiCnt": "624",
				"audiInten": "624",
				"audiChange": "100",
				"audiAcc": "1248",
				"scrnCnt": "1",
				"showCnt": "1"
			},
			{
				"rnum": "10",
				"rank": "10",
				"rankInten": "9",
				"rankOldAndNew": "OLD",
				"movieCd": "20184689",
				"movieNm": "아일라",
				"openDt": "2018-06-21",
				"salesAmt": "4151000",
				"salesShare": "0.2",
				"salesInten": "2266500",
				"salesChange": "120.3",
				"salesAcc": "317620400",
				"audiCnt": "607",
				"audiInten": "344",
				"audiChange": "130.8",
				"audiAcc": "41471",
				"scrnCnt": "11",
				"showCnt": "12"
			}
		]
	}
}