{
	"boxOfficeResult": {
		"boxofficeType": "일별 박스오피스",
		"showRange": "20180914~20180914",
		"dailyBoxOfficeList": [
			{
				"rnum": "1",
				"rank": "1",
				"rankInten": "0",
				"rankOldAndNew": "OLD",
				"movieCd": "20185046",
				"movieNm": "서치",
				"openDt": "2018-08-29",
				"salesAmt": "879483119",
				"salesShare": "67.5",
				"salesInten": "374907119",
				"salesChange": "74.3",
				"salesAcc": "17850107182",
				"audiCnt": "97668",
				"audiInten": "36491",
				"audiChange": "59.6",
				"audiAcc": "2109876",
				"scrnCnt": "845",
				"showCnt": "4268"
			},
			{
				"rnum": "2",
				"rank": "2",
				"rankInten": "0",
				"rankOldAndNew": "OLD",
				"movieCd": "20188581",
				"movieNm": "더 프레데터",
				"openDt": "2018-09-12",
				"salesAmt": "228883134",
				"salesShare": "17.6",
				"salesInten": "53883084",
				"salesChange": "30.8",
				"salesAcc": "644854384",
				"audiCnt": "25001",
				"audiInten": "3587",
				"audiChange": "16.8",
				"audiAcc": "75968",
				"scrnCnt": "572",
				"showCnt": "2714"
			},
			{
				"rnum": "3",
				"rank": "3",
				"rankInten": "0",
				"rankOldAndNew": "OLD",
				"movieCd": "20189362",
				"movieNm": "업그레이드",
				"openDt": "2018-09-06",
				"salesAmt": "71809500",
				"salesShare": "5.5",
				"salesInten": "26877000",
				"salesChange": "59.8",
				"salesAcc": "1359805400",
				"audiCnt": "7645",
				"audiInten": "2375",
				"audiChange": "45.1",
				"audiAcc": "148698",
				"scrnCnt": "167",
				"showCnt": "641"
			},
			{
				"rnum": "4",
				"rank": "4",
				"rankInten": "1",
				"rankOldAndNew": "OLD",
				"movieCd": "20181942",
				"movieNm": "맘마미아!2",
				"openDt": "2018-08-08",
				"salesAmt": "32506600",
				"salesShare": "2.5",
				"salesInten": "8485450",
				"salesChange": "35.3",
				"salesAcc": "19376637653",
				"audiCnt": "3578",
				"audiInten": "596",
				"audiChange": "20",
				"audiAcc": "2266775",
				"scrnCnt": "181",
				"showCnt": "310"
			},
			{
				"rnum": "5",
				"rank": "5",
				"rankInten": "1",
				"rankOldAndNew": "OLD",
				"movieCd": "20188567",
				"movieNm": "더 게스트",
				"openDt": "2018-09-12",
				"salesAmt": "16956700",
				"salesShare": "1.3",
				"salesInten": "2084200",
				"salesChange": "14",
				"salesAcc": "52254950",
				"audiCnt": "1797",
				"audiInten": "-3",
				"audiChange": "-0.2",
				"audiAcc": "6025",
				"scrnCnt": "228",
				"showCnt": "406"
			},
			{
				"rnum": "6",
				"rank": "6",
				"rankInten": "2",
				"rankOldAndNew": "OLD",
				"movieCd": "20188446",
				"movieNm": "양말요정 휴고의 대모험",
				"openDt": "2018-09-06",
				"salesAmt": "5199000",
				"salesShare": "0.4",
				"salesInten": "-73000",
				"salesChange": "-1.4",
				"salesAcc": "153170000",
				"audiCnt": "954",
				"audiInten": "43",
				"audiChange": "4.7",
				"audiAcc": "22646",
				"scrnCnt": "22",
				"showCnt": "24"
			},
			{
				"rnum": "7",
				"rank": "7",
				"rankInten": "0",
				"rankOldAndNew": "OLD",
				"movieCd": "20188242",
				"movieNm": "타샤 튜더",
				"openDt": "2018-09-13",
				"salesAmt": "6976500",
				"salesShare": "0.5",
				"salesInten": "130800",
				"salesChange": "1.9",
				"salesAcc": "19136200",
				"audiCnt": "909",
				"audiInten": "-78",
				"audiChange": "-7.9",
				"audiAcc": "2723",
				"scrnCnt": "23",
				"showCnt": "41"
			},
			{
				"rnum": "8",
				"rank": "8",
				"rankInten": "2",
				"rankOldAndNew": "OLD",
				"movieCd": "20189261",
				"movieNm": "어드리프트:우리가 함께한 바다",
				"openDt": "2018-09-06",
				"salesAmt": "7231100",
				"salesShare": "0.6",
				"salesInten": "1371100",
				"salesChange": "23.4",
				"salesAcc": "444182568",
				"audiCnt": "821",
				"audiInten": "79",
				"audiChange": "10.6",
				"audiAcc": "54423",
				"scrnCnt": "68",
				"showCnt": "94"
			},
			{
				"rnum": "9",
				"rank": "9",
				"rankInten": "0",
				"rankOldAndNew": "OLD",
				"movieCd": "20188342",
				"movieNm": "바니부기: 드래곤 에그를 찾아서",
				"openDt": "2018-09-12",
				"salesAmt": "5408800",
				"salesShare": "0.4",
				"salesInten": "977100",
				"salesChange": "22",
				"salesAcc": "16781500",
				"audiCnt": "766",
				"audiInten": "14",
				"audiChange": "1.9",
				"audiAcc": "2353",
				"scrnCnt": "109",
				"showCnt": "112"
			},
			{
				"rnum": "10",
				"rank": "10",
				"rankInten": "4",
				"rankOldAndNew": "OLD",
				"movieCd": "20187647",
				"movieNm": "나를 차버린 스파이",
				"openDt": "2018-08-22",
				"salesAmt": "4935500",
				"salesShare": "0.4",
				"salesInten": "1561500",
				"salesChange": "46.3",
				"salesAcc": "2319299500",
				"audiCnt": "505",
				"audiInten": "105",
				"audiChange": "26.3",
				"audiAcc": "261830",
				"scrnCnt": "31",
				"showCnt": "46"
			}
		]
	}
}