{
	"boxOfficeResult": {
		"boxofficeType": "일별 박스오피스",
		"showRange": "20180315~20180315",
		"dailyBoxOfficeList": [
			{
				"rnum": "1",
				"rank": "1",
				"rankInten": "0",
				"rankOldAndNew": "OLD",
				"movieCd": "20180302",
				"movieNm": "허리케인 하이스트",
				"openDt": "2018-03-14",
				"salesAmt": "147168300",
				"salesShare": "33.6",
				"salesInten": "2750000",
				"salesChange": "1.9",
				"salesAcc": "302003600",
				"audiCnt": "19532",
				"audiInten": "535",
				"audiChange": "2.8",
				"audiAcc": "39761",
				"scrnCnt": "485",
				"showCnt": "1768"
			},
			{
				"rnum": "2",
				"rank": "2",
				"rankInten": "0",
				"rankOldAndNew": "OLD",
				"movieCd": "20180564",
				"movieNm": "툼레이더",
				"openDt": "2018-03-08",
				"salesAmt": "99103600",
				"salesShare": "22.7",
				"salesInten": "-6982800",
				"salesChange": "-6.6",
				"salesAcc": "3786825704",
				"audiCnt": "13022",
				"audiInten": "-752",
				"audiChange": "-5.5",
				"audiAcc": "453694",
				"scrnCnt": "499",
				"showCnt": "1398"
			},
			{
				"rnum": "3",
				"rank": "3",
				"rankInten": "5",
				"rankOldAndNew": "OLD",
				"movieCd": "20178449",
				"movieNm": "쓰리 빌보드",
				"openDt": "2018-03-15",
				"salesAmt": "39847700",
				"salesShare": "9.1",
				"salesInten": "24723300",
				"salesChange": "163.5",
				"salesAcc": "90070400",
				"audiCnt": "5236",
				"audiInten": "3552",
				"audiChange": "210.9",
				"audiAcc": "11018",
				"scrnCnt": "88",
				"showCnt": "238"
			},
			{
				"rnum": "4",
				"rank": "4",
				"rankInten": "-1",
				"rankOldAndNew": "OLD",
				"movieCd": "20173436",
				"movieNm": "셰이프 오브 워터: 사랑의 모양",
				"openDt": "2018-02-22",
				"salesAmt": "32647400",
				"salesShare": "7.5",
				"salesInten": "-5559100",
				"salesChange": "-14.6",
				"salesAcc": "3758172500",
				"audiCnt": "4194",
				"audiInten": "-733",
				"audiChange": "-14.9",
				"audiAcc": "452615",
				"scrnCnt": "178",
				"showCnt": "307"
			},
			{
				"rnum": "5",
				"rank": "5",
				"rankInten": "-1",
				"rankOldAndNew": "OLD",
				"movieCd": "20180082",
				"movieNm": "로건 럭키",
				"openDt": "2018-03-14",
				"salesAmt": "20872300",
				"salesShare": "4.8",
				"salesInten": "-2231500",
				"salesChange": "-9.7",
				"salesAcc": "50669600",
				"audiCnt": "2856",
				"audiInten": "-382",
				"audiChange": "-11.8",
				"audiAcc": "6946",
				"scrnCnt": "255",
				"showCnt": "502"
			},
			{
				"rnum": "6",
				"rank": "6",
				"rankInten": "1",
				"rankOldAndNew": "OLD",
				"movieCd": "20170561",
				"movieNm": "블랙 팬서",
				"openDt": "2018-02-14",
				"salesAmt": "16582700",
				"salesShare": "3.8",
				"salesInten": "-636300",
				"salesChange": "-3.7",
				"salesAcc": "45567958357",
				"audiCnt": "2184",
				"audiInten": "-127",
				"audiChange": "-5.5",
				"audiAcc": "5359496",
				"scrnCnt": "138",
				"showCnt": "204"
			},
			{
				"rnum": "7",
				"rank": "7",
				"rankInten": "-1",
				"rankOldAndNew": "OLD",
				"movieCd": "20177946",
				"movieNm": "월요일이 사라졌다",
				"openDt": "2018-02-22",
				"salesAmt": "16816200",
				"salesShare": "3.8",
				"salesInten": "-2301400",
				"salesChange": "-12",
				"salesAcc": "7350171800",
				"audiCnt": "2133",
				"audiInten": "-254",
				"audiChange": "-10.6",
				"audiAcc": "886521",
				"scrnCnt": "112",
				"showCnt": "229"
			},
			{
				"rnum": "8",
				"rank": "8",
				"rankInten": "-3",
				"rankOldAndNew": "OLD",
				"movieCd": "20176070",
				"movieNm": "플로리다 프로젝트",
				"openDt": "2018-03-07",
				"salesAmt": "16126400",
				"salesShare": "3.7",
				"salesInten": "-4011000",
				"salesChange": "-19.9",
				"salesAcc": "440790400",
				"audiCnt": "2066",
				"audiInten": "-466",
				"audiChange": "-18.4",
				"audiAcc": "52786",
				"scrnCnt": "68",
				"showCnt": "124"
			},
			{
				"rnum": "9",
				"rank": "9",
				"rankInten": "0",
				"rankOldAndNew": "OLD",
				"movieCd": "20189861",
				"movieNm": "더 포스트",
				"openDt": "2018-02-28",
				"salesAmt": "10442100",
				"salesShare": "2.4",
				"salesInten": "-689100",
				"salesChange": "-6.2",
				"salesAcc": "937659000",
				"audiCnt": "1392",
				"audiInten": "-99",
				"audiChange": "-6.6",
				"audiAcc": "118814",
				"scrnCnt": "68",
				"showCnt": "90"
			},
			{
				"rnum": "10",
				"rank": "10",
				"rankInten": "0",
				"rankOldAndNew": "NEW",
				"movieCd": "20181792",
				"movieNm": "극장판 마법소녀 마도카 마기카(신편): 반역의 이야기",
				"openDt": "2018-03-15",
				"salesAmt": "5954000",
				"salesShare": "1.4",
				"salesInten": "5954000",
				"salesChange": "100",
				"salesAcc": "5954000",
				"audiCnt": "800",
				"audiInten": "800",
				"audiChange": "100",
				"audiAcc": "800",
				"scrnCnt": "61",
				"showCnt": "98"
			}
		]
	}
}