{
	"boxOfficeResult": {
		"boxofficeType": "일별 박스오피스",
		"showRange": "20170101~20170101",
		"dailyBoxOfficeList": [
			{
				"rnum": "1",
				"rank": "1",
				"rankInten": "0",
				"rankOldAndNew": "OLD",
				"movieCd": "20161725",
				"movieNm": "마스터",
				"openDt": "2016-12-21",
				"salesAmt": "4399793100",
				"salesShare": "82.9",
				"salesInten": "-183705150",
				"salesChange": "-4",
				"salesAcc": "44184434165",
				"audiCnt": "506299",
				"audiInten": "-31485",
				"audiChange": "-5.9",
				"audiAcc": "5441619",
				"scrnCnt": "1245",
				"showCnt": "5721"
			},
			{
				"rnum": "2",
				"rank": "2",
				"rankInten": "0",
				"rankOldAndNew": "OLD",
				"movieCd": "20144641",
				"movieNm": "판도라",
				"openDt": "2016-12-07",
				"salesAmt": "736891900",
				"salesShare": "13.9",
				"salesInten": "-35339100",
				"salesChange": "-4.6",
				"salesAcc": "34692290064",
				"audiCnt": "87966",
				"audiInten": "-6799",
				"audiChange": "-7.2",
				"audiAcc": "4401830",
				"scrnCnt": "576",
				"showCnt": "1476"
			},
			{
				"rnum": "3",
				"rank": "3",
				"rankInten": "0",
				"rankOldAndNew": "OLD",
				"movieCd": "20152371",
				"movieNm": "당신, 거기 있어줄래요",
				"openDt": "2016-12-14",
				"salesAmt": "166222000",
				"salesShare": "3.1",
				"salesInten": "-30383700",
				"salesChange": "-15.5",
				"salesAcc": "9165307248",
				"audiCnt": "18630",
				"audiInten": "-4126",
				"audiChange": "-18.1",
				"audiAcc": "1143445",
				"scrnCnt": "261",
				"showCnt": "572"
			},
			{
				"rnum": "4",
				"rank": "4",
				"rankInten": "0",
				"rankOldAndNew": "OLD",
				"movieCd": "20154661",
				"movieNm": "형",
				"openDt": "2016-11-23",
				"salesAmt": "944000",
				"salesShare": "0.0",
				"salesInten": "-627000",
				"salesChange": "-39.9",
				"salesAcc": "23114712293",
				"audiCnt": "123",
				"audiInten": "-85",
				"audiChange": "-40.9",
				"audiAcc": "2979782",
				"scrnCnt": "8",
				"showCnt": "9"
			},
			{
				"rnum": "5",
				"rank": "5",
				"rankInten": "0",
				"rankOldAndNew": "OLD",
				"movieCd": "20161701",
				"movieNm": "위켄즈",
				"openDt": "2016-12-22",
				"salesAmt": "765700",
				"salesShare": "0.0",
				"salesInten": "-964300",
				"salesChange": "-55.7",
				"salesAcc": "17988700",
				"audiCnt": "93",
				"audiInten": "-101",
				"audiChange": "-52.1",
				"audiAcc": "2354",
				"scrnCnt": "10",
				"showCnt": "11"
			},
			{
				"rnum": "6",
				"rank": "6",
				"rankInten": "5",
				"rankOldAndNew": "OLD",
				"movieCd": "20161603",
				"movieNm": "순종",
				"openDt": "2016-11-17",
				"salesAmt": "447000",
				"salesShare": "0.0",
				"salesInten": "241000",
				"salesChange": "117",
				"salesAcc": "385404200",
				"audiCnt": "73",
				"audiInten": "48",
				"audiChange": "192",
				"audiAcc": "54529",
				"scrnCnt": "2",
				"showCnt": "2"
			},
			{
				"rnum": "7",
				"rank": "7",
				"rankInten": "-1",
				"rankOldAndNew": "OLD",
				"movieCd": "20162545",
				"movieNm": "무현, 두 도시 이야기",
				"openDt": "2016-10-26",
				"salesAmt": "410000",
				"salesShare": "0.0",
				"salesInten": "-309600",
				"salesChange": "-43",
				"salesAcc": "1511840600",
				"audiCnt": "60",
				"audiInten": "-35",
				"audiChange": "-36.8",
				"audiAcc": "192728",
				"scrnCnt": "5",
				"showCnt": "6"
			},
			{
				"rnum": "8",
				"rank": "8",
				"rankInten": "-1",
				"rankOldAndNew": "OLD",
				"movieCd": "20159286",
				"movieNm": "연애담",
				"openDt": "2016-11-17",
				"salesAmt": "315000",
				"salesShare": "0.0",
				"salesInten": "-149000",
				"salesChange": "-32.1",
				"salesAcc": "183011100",
				"audiCnt": "38",
				"audiInten": "-26",
				"audiChange": "-40.6",
				"audiAcc": "22418",
				"scrnCnt": "3",
				"showCnt": "3"
			},
			{
				"rnum": "9",
				"rank": "9",
				"rankInten": "0",
				"rankOldAndNew": "OLD",
				"movieCd": "20164527",
				"movieNm": "부릉! 부릉! 브루미즈: 스피더의 모험 일기",
				"openDt": "2016-12-15",
				"salesAmt": "186000",
				"salesShare": "0.0",
				"salesInten": "-76500",
				"salesChange": "-29.1",
				"salesAcc": "81314500",
				"audiCnt": "21",
				"audiInten": "-12",
				"audiChange": "-36.4",
				"audiAcc": "10229",
				"scrnCnt": "3",
				"showCnt": "3"
			},
			{
				"rnum": "10",
				"rank": "10",
				"rankInten": "3",
				"rankOldAndNew": "OLD",
				"movieCd": "20153401",
				"movieNm": "파파좀비",
				"openDt": "2016-12-29",
				"salesAmt": "109000",
				"salesShare": "0.0",
				"salesInten": "-28500",
				"salesChange": "-20.7",
				"salesAcc": "1704500",
				"audiCnt": "18",
				"audiInten": "0",
				"audiChange": "0",
				"audiAcc": "274",
				"scrnCnt": "4",
				"showCnt": "4"
			}
		]
	}
}